kfe/dependencies.py
kfe/directory_context.py
kfe/main.py
kfe/schema.json
kfe/dtos/mappers.py
kfe/dtos/request.py
kfe/dtos/response.py
kfe/endpoints/access.py
kfe/endpoints/directories.py
kfe/endpoints/load.py
kfe/endpoints/metadata.py
kfe/features/clip_engine.py
kfe/features/lemmatizer.py
kfe/features/ocr_engine.py
kfe/features/text_embedding_engine.py
kfe/features/transcriber.py
kfe/features/audioutils/dictionary_assisted_decoder.py
kfe/huggingsound/decoder.py
kfe/huggingsound/model.py
kfe/huggingsound/token_set.py
kfe/huggingsound/utils.py
kfe/persistence/db.py
kfe/persistence/directory_repository.py
kfe/persistence/embeddings.py
kfe/persistence/file_metadata_repository.py
kfe/persistence/model.py
kfe/resources/frontend_build/asset-manifest.json
kfe/resources/frontend_build/favicon.ico
kfe/resources/frontend_build/index.html
kfe/resources/frontend_build/logo192.png
kfe/resources/frontend_build/logo512.png
kfe/resources/frontend_build/manifest.json
kfe/resources/frontend_build/robots.txt
kfe/resources/frontend_build/static/css/main.d4dcab1c.css
kfe/resources/frontend_build/static/css/main.d4dcab1c.css.map
kfe/resources/frontend_build/static/js/main.e1b93572.js
kfe/resources/frontend_build/static/js/main.e1b93572.js.LICENSE.txt
kfe/resources/frontend_build/static/js/main.e1b93572.js.map
kfe/search/embedding_similarity_calculator.py
kfe/search/lexical_search_engine.py
kfe/search/models.py
kfe/search/multi_embedding_similarity_calculator.py
kfe/search/query_parser.py
kfe/search/reverse_index.py
kfe/search/token_stat_counter.py
kfe/search/tokenizer.py
kfe/service/embedding_processor.py
kfe/service/file_indexer.py
kfe/service/metadata_editor.py
kfe/service/ocr_service.py
kfe/service/search.py
kfe/service/thumbnails.py
kfe/service/transcription_service.py
kfe/utils/constants.py
kfe/utils/ffprobe.py
kfe/utils/file_access.py
kfe/utils/file_change_watcher.py
kfe/utils/hybrid_search_confidence_providers.py
kfe/utils/init_progress_tracker.py
kfe-1.1.2.dist-info/METADATA
kfe-1.1.2.dist-info/WHEEL
kfe-1.1.2.dist-info/entry_points.txt
kfe-1.1.2.dist-info/top_level.txt
kfe-1.1.2.dist-info/RECORD
