Metadata-Version: 2.2
Name: kfe
Version: 1.1.2
Summary: File Explorer and Search Engine for locally stored multimedia
Author-email: flok3n@gmail.com
License: MIT License
Project-URL: Repository, https://github.com/Fl0k3n/kfe
Keywords: file explorer,search engine,multimedia,video,audio,image,semantic,lexical,clip,transcription,gui
Classifier: Programming Language :: Python
Classifier: Topic :: Desktop Environment
Classifier: Topic :: Multimedia
Classifier: Operating System :: OS Independent
Requires-Python: >=3.10
Requires-Dist: aiofiles<25.0,>=24.1.0
Requires-Dist: aiosqlite<1.0,>=0.20.0
Requires-Dist: accelerate<2.0,>=1.2.0
Requires-Dist: easyocr<2.0,>=1.7.1
Requires-Dist: editdistance<1.0,>=0.8.1
Requires-Dist: fastapi[standard]>=0.112.2
Requires-Dist: torch<3.0,>=2.4.1
Requires-Dist: msgpack<2.0,>=1.1.0
Requires-Dist: numpy<2.0,>=1.26.4
Requires-Dist: einops<1.0,>=0.8
Requires-Dist: pillow<11.0,>=10.4.0
Requires-Dist: spacy==3.7.5
Requires-Dist: spacy-curated-transformers==0.2.2
Requires-Dist: pydantic<3.0,>=2.8.2
Requires-Dist: sentence-transformers<4.0,>=3.1.0
Requires-Dist: SQLAlchemy<3.0,>=2.0.32
Requires-Dist: tqdm>=4.0
Requires-Dist: transformers<5.0,>=4.44.2
Requires-Dist: watchdog<6.0,>=5.0.3
Requires-Dist: wordfreq<4.0,>=3.1.1
Requires-Dist: librosa<1.0,>=0.9.2
Requires-Dist: lru-dict<2.0,>=1.3.0
Requires-Dist: greenlet<4.0,>=3.1.1
Requires-Dist: certifi>=2024.8
